XaiGrokSDK.py
xai_grok/__init__.py
xai_grok/sdk.py
xai_grok/utils.py
xai_grok_sdk_advanced-1.3.0.dist-info/LICENSE
xai_grok_sdk_advanced-1.3.0.dist-info/METADATA
xai_grok_sdk_advanced-1.3.0.dist-info/WHEEL
xai_grok_sdk_advanced-1.3.0.dist-info/entry_points.txt
xai_grok_sdk_advanced-1.3.0.dist-info/top_level.txt
xai_grok_sdk_advanced-1.3.0.dist-info/RECORD
